Metadata-Version: 1.0
Name: daynextprev
Version: 0.0.5
Summary: calculate next/prev day from y/m/d input
Home-page: https://github.com/tomotaka/day-nextprev
Author: Tomotaka Ito
Author-email: tomotaka.ito@gmail.com
License: Copyright 2017 Tomotaka Ito
